{"filename":"C:\\Users\\Nemanja\\Desktop\\fax\\Kolokvijumi i cuda za fax\\4 god\\2 semestar\\cloud\\projekat\\__azurite_db_queue_extent__.json","collections":[{"name":"$EXTENTS_COLLECTION$","data":[{"id":"4eb0ec49-1366-42aa-93bf-8378c9f0700c","locationId":"Default","path":"4eb0ec49-1366-42aa-93bf-8378c9f0700c","size":5284,"lastModifiedInMS":1779905094360,"meta":{"revision":12,"created":1779905094361,"version":0,"updated":1779905890081},"$loki":22,"LastModifyInMS":1779905890081},{"id":"ea53390e-725b-4d90-8125-8f11d1994536","locationId":"Default","path":"ea53390e-725b-4d90-8125-8f11d1994536","size":2836,"lastModifiedInMS":1779906822893,"meta":{"revision":6,"created":1779906822893,"version":0,"updated":1779907223685},"$loki":24,"LastModifyInMS":1779907223685},{"id":"129d802a-ca5e-450b-8a58-c931dc7c7dd5","locationId":"Default","path":"129d802a-ca5e-450b-8a58-c931dc7c7dd5","size":808,"lastModifiedInMS":1779907305104,"meta":{"revision":1,"created":1779907305105,"version":0,"updated":1779907310380},"$loki":25,"LastModifyInMS":1779907310380},{"id":"2765c3bd-a25f-4953-bd9a-c628cc0626b0","locationId":"Default","path":"2765c3bd-a25f-4953-bd9a-c628cc0626b0","size":1212,"lastModifiedInMS":1779984092150,"meta":{"revision":2,"created":1779984092151,"version":0,"updated":1779984145796},"$loki":35,"LastModifyInMS":1779984145796},{"id":"fb049649-830c-4f8b-88fc-9b3fa7709062","locationId":"Default","path":"fb049649-830c-4f8b-88fc-9b3fa7709062","size":404,"lastModifiedInMS":1779984639651,"meta":{"revision":0,"created":1779984639652,"version":0},"$loki":36}],"idIndex":null,"binaryIndices":{"id":{"name":"id","dirty":false,"values":[2,3,0,1,4]}},"constraints":null,"uniqueNames":[],"transforms":{},"objType":"$EXTENTS_COLLECTION$","dirty":false,"cachedIndex":null,"cachedBinaryIndex":null,"cachedData":null,"adaptiveBinaryIndices":true,"transactional":false,"cloneObjects":false,"cloneMethod":"parse-stringify","asyncListeners":false,"disableMeta":false,"disableChangesApi":true,"disableDeltaChangesApi":true,"autoupdate":false,"serializableIndices":true,"disableFreeze":true,"ttl":null,"maxId":36,"DynamicViews":[],"events":{"insert":[],"update":[],"pre-insert":[],"pre-update":[],"close":[],"flushbuffer":[],"error":[],"delete":[null],"warning":[null]},"changes":[],"dirtyIds":[]}],"databaseVersion":1.5,"engineVersion":1.5,"autosave":true,"autosaveInterval":5000,"autosaveHandle":null,"throttledSaves":true,"options":{"persistenceMethod":"fs","autosave":true,"autosaveInterval":5000,"serializationMethod":"normal","destructureDelimiter":"$<\n"},"persistenceMethod":"fs","persistenceAdapter":null,"verbose":false,"events":{"init":[null],"loaded":[],"flushChanges":[],"close":[],"changes":[],"warning":[]},"ENV":"NODEJS"}